<?xml version="1.0" encoding="UTF-8" ?>
<!DOCTYPE mapper PUBLIC "-//mybatis.org//DTD Mapper 3.0//EN" "http://mybatis.org/dtd/mybatis-3-mapper.dtd">

<mapper namespace="cn.thinkjoy.gk.dao.IUniversityDAO">
<!--
insert
update
updateNull
deleteById
deleteByCondition
deleteByProperty
fetch
findOne
findList
findAll
queryPage
like
queryList
queryOne
count
selectMaxId
updateOrSave
selectOne
selectList
-->
    <sql id="Base_Column_List">
        id,
        createDate,
        status,
        creator,
        lastModDate,
        lastModifier,
        code,
        name,
        subjection,
        educationLevel,
        property,
        type,
        url,
        address,
        contactPhone,
        entranceIntro,
        universityIntro,
        provinceId,
        provinceName,
        cityId,
        cityName,
        countyId,
        countyName,
        batchType
    </sql>
    <insert id="insert" parameterType="University">
        INSERT INTO gk_university (
        createDate,
        status,
        creator,
        lastModDate,
        lastModifier,
        code,
        name,
        subjection,
        educationLevel,
        property,
        type,
        url,
        address,
        contactPhone,
        entranceIntro,
        universityIntro,
        provinceId,
        provinceName,
        cityId,
        cityName,
        countyId,
        countyName,
        batchType
        ) VALUES (
        #{createDate},
        #{status},
        #{creator},
        #{lastModDate},
        #{lastModifier},
        #{code},
        #{name},
        #{subjection},
        #{educationLevel},
        #{property},
        #{type},
        #{url},
        #{address},
        #{contactPhone},
        #{entranceIntro},
        #{universityIntro},
        #{provinceId},
        #{provinceName},
        #{cityId},
        #{cityName},
        #{countyId},
        #{countyName},
        #{batchType}
        )
        <selectKey resultType="java.lang.Long" keyProperty="id">
        SELECT LAST_INSERT_ID() AS ID
        </selectKey>
    </insert>

    <!-- 更新 -->
    <update id="update" parameterType="University">
        UPDATE gk_university
        <trim prefix="SET" suffixOverrides=",">
            <if test="createDate!=null">
                createDate = #{createDate},
            </if>
            <if test="status!=null">
                status = #{status},
            </if>
            <if test="creator!=null">
                creator = #{creator},
            </if>
            <if test="lastModDate!=null">
                lastModDate = #{lastModDate},
            </if>
            <if test="lastModifier!=null">
                lastModifier = #{lastModifier},
            </if>
            <if test="code!=null">
                code = #{code},
            </if>
            <if test="name!=null">
                name = #{name},
            </if>
            <if test="subjection!=null">
                subjection = #{subjection},
            </if>
            <if test="educationLevel!=null">
                educationLevel = #{educationLevel},
            </if>
            <if test="property!=null">
                property = #{property},
            </if>
            <if test="type!=null">
                type = #{type},
            </if>
            <if test="url!=null">
                url = #{url},
            </if>
            <if test="address!=null">
                address = #{address},
            </if>
            <if test="contactPhone!=null">
                contactPhone = #{contactPhone},
            </if>
            <if test="entranceIntro!=null">
                entranceIntro = #{entranceIntro},
            </if>
            <if test="universityIntro!=null">
                universityIntro = #{universityIntro},
            </if>
            <if test="provinceId!=null">
                provinceId = #{provinceId},
            </if>
            <if test="provinceName!=null">
                provinceName = #{provinceName},
            </if>
            <if test="cityId!=null">
                cityId = #{cityId},
            </if>
            <if test="cityName!=null">
                cityName = #{cityName},
            </if>
            <if test="countyId!=null">
                countyId = #{countyId},
            </if>
            <if test="countyName!=null">
                countyName = #{countyName},
            </if>
            <if test="batchType!=null">
                batchType = #{batchType},
            </if>
        </trim>
        WHERE
        id = #{id}
    </update>

    <update id="updateMap">
        UPDATE gk_university
        <trim prefix="SET" suffixOverrides=",">
            <if test="map.createDate!=null">
                createDate = #{map.createDate},
            </if>
            <if test="map.status!=null">
                status = #{map.status},
            </if>
            <if test="map.creator!=null">
                creator = #{map.creator},
            </if>
            <if test="map.lastModDate!=null">
                lastModDate = #{map.lastModDate},
            </if>
            <if test="map.lastModifier!=null">
                lastModifier = #{map.lastModifier},
            </if>
            <if test="map.code!=null">
                code = #{map.code},
            </if>
            <if test="map.name!=null">
                name = #{map.name},
            </if>
            <if test="map.subjection!=null">
                subjection = #{map.subjection},
            </if>
            <if test="map.educationLevel!=null">
                educationLevel = #{map.educationLevel},
            </if>
            <if test="map.property!=null">
                property = #{map.property},
            </if>
            <if test="map.type!=null">
                type = #{map.type},
            </if>
            <if test="map.url!=null">
                url = #{map.url},
            </if>
            <if test="map.address!=null">
                address = #{map.address},
            </if>
            <if test="map.contactPhone!=null">
                contactPhone = #{map.contactPhone},
            </if>
            <if test="map.entranceIntro!=null">
                entranceIntro = #{map.entranceIntro},
            </if>
            <if test="map.universityIntro!=null">
                universityIntro = #{map.universityIntro},
            </if>
            <if test="map.provinceId!=null">
                provinceId = #{map.provinceId},
            </if>
            <if test="map.provinceName!=null">
                provinceName = #{map.provinceName},
            </if>
            <if test="map.cityId!=null">
                cityId = #{map.cityId},
            </if>
            <if test="map.cityName!=null">
                cityName = #{map.cityName},
            </if>
            <if test="map.countyId!=null">
                countyId = #{map.countyId},
            </if>
            <if test="map.countyName!=null">
                countyName = #{map.countyName},
            </if>
            <if test="map.batchType!=null">
                batchType = #{map.batchType},
            </if>
        </trim>
        WHERE
        id = #{map.id}
    </update>

    <update id="updateByCondition">
        UPDATE gk_university
        <trim prefix="SET" suffixOverrides=",">
            <if test="update.createDate!=null">
                createDate = #{update.createDate},
            </if>
            <if test="update.status!=null">
                status = #{update.status},
            </if>
            <if test="update.creator!=null">
                creator = #{update.creator},
            </if>
            <if test="update.lastModDate!=null">
                lastModDate = #{update.lastModDate},
            </if>
            <if test="update.lastModifier!=null">
                lastModifier = #{update.lastModifier},
            </if>
            <if test="update.code!=null">
                code = #{update.code},
            </if>
            <if test="update.name!=null">
                name = #{update.name},
            </if>
            <if test="update.subjection!=null">
                subjection = #{update.subjection},
            </if>
            <if test="update.educationLevel!=null">
                educationLevel = #{update.educationLevel},
            </if>
            <if test="update.property!=null">
                property = #{update.property},
            </if>
            <if test="update.type!=null">
                type = #{update.type},
            </if>
            <if test="update.url!=null">
                url = #{update.url},
            </if>
            <if test="update.address!=null">
                address = #{update.address},
            </if>
            <if test="update.contactPhone!=null">
                contactPhone = #{update.contactPhone},
            </if>
            <if test="update.entranceIntro!=null">
                entranceIntro = #{update.entranceIntro},
            </if>
            <if test="update.universityIntro!=null">
                universityIntro = #{update.universityIntro},
            </if>
            <if test="update.provinceId!=null">
                provinceId = #{update.provinceId},
            </if>
            <if test="update.provinceName!=null">
                provinceName = #{update.provinceName},
            </if>
            <if test="update.cityId!=null">
                cityId = #{update.cityId},
            </if>
            <if test="update.cityName!=null">
                cityName = #{update.cityName},
            </if>
            <if test="update.countyId!=null">
                countyId = #{update.countyId},
            </if>
            <if test="update.countyName!=null">
                countyName = #{update.countyName},
            </if>
            <if test="update.batchType!=null">
                batchType = #{update.batchType},
            </if>
        </trim>

        <trim prefix="WHERE" prefixOverrides="AND | OR">
            <if test="condition.id!=null">
                AND id = #{condition.id}
            </if>
            <if test="condition.createDate!=null">
                AND createDate = #{condition.createDate}
            </if>
            <if test="condition.status!=null">
                AND status = #{condition.status}
            </if>
            <if test="condition.creator!=null">
                AND creator = #{condition.creator}
            </if>
            <if test="condition.lastModDate!=null">
                AND lastModDate = #{condition.lastModDate}
            </if>
            <if test="condition.lastModifier!=null">
                AND lastModifier = #{condition.lastModifier}
            </if>
            <if test="condition.code!=null">
                AND code = #{condition.code}
            </if>
            <if test="condition.name!=null">
                AND name = #{condition.name}
            </if>
            <if test="condition.subjection!=null">
                AND subjection = #{condition.subjection}
            </if>
            <if test="condition.educationLevel!=null">
                AND educationLevel = #{condition.educationLevel}
            </if>
            <if test="condition.property!=null">
                AND property = #{condition.property}
            </if>
            <if test="condition.type!=null">
                AND type = #{condition.type}
            </if>
            <if test="condition.url!=null">
                AND url = #{condition.url}
            </if>
            <if test="condition.address!=null">
                AND address = #{condition.address}
            </if>
            <if test="condition.contactPhone!=null">
                AND contactPhone = #{condition.contactPhone}
            </if>
            <if test="condition.entranceIntro!=null">
                AND entranceIntro = #{condition.entranceIntro}
            </if>
            <if test="condition.universityIntro!=null">
                AND universityIntro = #{condition.universityIntro}
            </if>
            <if test="condition.provinceId!=null">
                AND provinceId = #{condition.provinceId}
            </if>
            <if test="condition.provinceName!=null">
                AND provinceName = #{condition.provinceName}
            </if>
            <if test="condition.cityId!=null">
                AND cityId = #{condition.cityId}
            </if>
            <if test="condition.cityName!=null">
                AND cityName = #{condition.cityName}
            </if>
            <if test="condition.countyId!=null">
                AND countyId = #{condition.countyId}
            </if>
            <if test="condition.countyName!=null">
                AND countyName = #{condition.countyName}
            </if>
            <if test="condition.batchType!=null">
                AND batchType = #{condition.batchType}
            </if>
        </trim>
    </update>

    <insert id="insertMap" >
        INSERT INTO gk_university (
                createDate,
                status,
                creator,
                lastModDate,
                lastModifier,
                code,
                name,
                subjection,
                educationLevel,
                property,
                type,
                url,
                address,
                contactPhone,
                entranceIntro,
                universityIntro,
                provinceId,
                provinceName,
                cityId,
                cityName,
                countyId,
                countyName,
                batchType
        ) VALUES (
                    #{map.createDate},
                    #{map.status},
                    #{map.creator},
                    #{map.lastModDate},
                    #{map.lastModifier},
                    #{map.code},
                    #{map.name},
                    #{map.subjection},
                    #{map.educationLevel},
                    #{map.property},
                    #{map.type},
                    #{map.url},
                    #{map.address},
                    #{map.contactPhone},
                    #{map.entranceIntro},
                    #{map.universityIntro},
                    #{map.provinceId},
                    #{map.provinceName},
                    #{map.cityId},
                    #{map.cityName},
                    #{map.countyId},
                    #{map.countyName},
                    #{map.batchType}
        )
    </insert>


    <update id="updateNull" parameterType="University">
        UPDATE gk_university
        <trim prefix="SET" suffixOverrides=",">
            createDate = #{createDate},
            status = #{status},
            creator = #{creator},
            lastModDate = #{lastModDate},
            lastModifier = #{lastModifier},
            code = #{code},
            name = #{name},
            subjection = #{subjection},
            educationLevel = #{educationLevel},
            property = #{property},
            type = #{type},
            url = #{url},
            address = #{address},
            contactPhone = #{contactPhone},
            entranceIntro = #{entranceIntro},
            universityIntro = #{universityIntro},
            provinceId = #{provinceId},
            provinceName = #{provinceName},
            cityId = #{cityId},
            cityName = #{cityName},
            countyId = #{countyId},
            countyName = #{countyName},
            batchType = #{batchType},
        </trim>
        WHERE
        id = #{id} 
    </update>

    <!-- 按Id删除 -->
    <delete id="deleteById" parameterType="java.lang.Long">
        DELETE FROM gk_university
        <trim prefix="WHERE" prefixOverrides="AND | OR">
            AND id = #{id}
        </trim>
    </delete>


    <delete id="deleteByCondition" parameterType="java.util.Map">
        DELETE FROM gk_university
        <trim prefix="WHERE" prefixOverrides="AND | OR">
            <if test="id!=null">
                AND id = #{id}
            </if>
            <if test="createDate!=null">
                AND createDate = #{createDate}
            </if>
            <if test="status!=null">
                AND status = #{status}
            </if>
            <if test="creator!=null">
                AND creator = #{creator}
            </if>
            <if test="lastModDate!=null">
                AND lastModDate = #{lastModDate}
            </if>
            <if test="lastModifier!=null">
                AND lastModifier = #{lastModifier}
            </if>
            <if test="code!=null">
                AND code = #{code}
            </if>
            <if test="name!=null">
                AND name = #{name}
            </if>
            <if test="subjection!=null">
                AND subjection = #{subjection}
            </if>
            <if test="educationLevel!=null">
                AND educationLevel = #{educationLevel}
            </if>
            <if test="property!=null">
                AND property = #{property}
            </if>
            <if test="type!=null">
                AND type = #{type}
            </if>
            <if test="url!=null">
                AND url = #{url}
            </if>
            <if test="address!=null">
                AND address = #{address}
            </if>
            <if test="contactPhone!=null">
                AND contactPhone = #{contactPhone}
            </if>
            <if test="entranceIntro!=null">
                AND entranceIntro = #{entranceIntro}
            </if>
            <if test="universityIntro!=null">
                AND universityIntro = #{universityIntro}
            </if>
            <if test="provinceId!=null">
                AND provinceId = #{provinceId}
            </if>
            <if test="provinceName!=null">
                AND provinceName = #{provinceName}
            </if>
            <if test="cityId!=null">
                AND cityId = #{cityId}
            </if>
            <if test="cityName!=null">
                AND cityName = #{cityName}
            </if>
            <if test="countyId!=null">
                AND countyId = #{countyId}
            </if>
            <if test="countyName!=null">
                AND countyName = #{countyName}
            </if>
            <if test="batchType!=null">
                AND batchType = #{batchType}
            </if>
        </trim>
    </delete>

    <delete id="deleteByProperty" parameterType="java.util.Map">
        DELETE FROM gk_university WHERE
        ${property} = #{value}
    </delete>

    <select id="fetch" parameterType="java.lang.Long" resultType="University">
        SELECT
        <include refid="Base_Column_List" />
        FROM gk_university
        <trim prefix="WHERE" prefixOverrides="AND | OR">
            AND id = #{id}
        </trim>
        <if test="orderBy!=null">
        ORDER BY ${orderBy} ${sortBy}
        </if>
    </select>

    <select id="findOne" parameterType="java.util.Map" resultType="University">
        SELECT
        <include refid="Base_Column_List" />
        FROM gk_university WHERE
        ${property} = #{value}
        LIMIT 0,1
    </select>

    <select id="findList" parameterType="java.util.Map" resultType="University">
        SELECT
        <include refid="Base_Column_List" />
        FROM gk_university WHERE
        ${property} = #{value}
        <if test="orderBy!=null">
            ORDER BY ${orderBy} ${sortBy}
        </if>
    </select>

    <select id="findAll" resultType="University">
        SELECT
        <include refid="Base_Column_List" />
        FROM gk_university
        <if test="orderBy!=null">
            ORDER BY ${orderBy} ${sortBy}
        </if>
    </select>

    <select id="queryPage" resultType="University">
        SELECT
        <include refid="Base_Column_List" />
        FROM gk_university
        <where>

            <if test="condition.whereSql != null">
                and id in (#{condition.whereSql})
            </if>

            <if test="condition.id!=null">
                ${condition.groupOp}   id  ${condition.id.op}  #{condition.id.data}
            </if>
            <if test="condition.createDate!=null">
                ${condition.groupOp}   createDate  ${condition.createDate.op}  #{condition.createDate.data}
            </if>
            <if test="condition.status!=null">
                ${condition.groupOp}   status  ${condition.status.op}  #{condition.status.data}
            </if>
            <if test="condition.creator!=null">
                ${condition.groupOp}   creator  ${condition.creator.op}  #{condition.creator.data}
            </if>
            <if test="condition.lastModDate!=null">
                ${condition.groupOp}   lastModDate  ${condition.lastModDate.op}  #{condition.lastModDate.data}
            </if>
            <if test="condition.lastModifier!=null">
                ${condition.groupOp}   lastModifier  ${condition.lastModifier.op}  #{condition.lastModifier.data}
            </if>
            <if test="condition.code!=null">
                ${condition.groupOp}   code  ${condition.code.op}  #{condition.code.data}
            </if>
            <if test="condition.name!=null">
                ${condition.groupOp}   name  ${condition.name.op}  #{condition.name.data}
            </if>
            <if test="condition.subjection!=null">
                ${condition.groupOp}   subjection  ${condition.subjection.op}  #{condition.subjection.data}
            </if>
            <if test="condition.educationLevel!=null">
                ${condition.groupOp}   educationLevel  ${condition.educationLevel.op}  #{condition.educationLevel.data}
            </if>
            <if test="condition.property!=null">
                ${condition.groupOp}   property  ${condition.property.op}  #{condition.property.data}
            </if>
            <if test="condition.type!=null">
                ${condition.groupOp}   type  ${condition.type.op}  #{condition.type.data}
            </if>
            <if test="condition.url!=null">
                ${condition.groupOp}   url  ${condition.url.op}  #{condition.url.data}
            </if>
            <if test="condition.address!=null">
                ${condition.groupOp}   address  ${condition.address.op}  #{condition.address.data}
            </if>
            <if test="condition.contactPhone!=null">
                ${condition.groupOp}   contactPhone  ${condition.contactPhone.op}  #{condition.contactPhone.data}
            </if>
            <if test="condition.entranceIntro!=null">
                ${condition.groupOp}   entranceIntro  ${condition.entranceIntro.op}  #{condition.entranceIntro.data}
            </if>
            <if test="condition.universityIntro!=null">
                ${condition.groupOp}   universityIntro  ${condition.universityIntro.op}  #{condition.universityIntro.data}
            </if>
            <if test="condition.provinceId!=null">
                ${condition.groupOp}   provinceId  ${condition.provinceId.op}  #{condition.provinceId.data}
            </if>
            <if test="condition.provinceName!=null">
                ${condition.groupOp}   provinceName  ${condition.provinceName.op}  #{condition.provinceName.data}
            </if>
            <if test="condition.cityId!=null">
                ${condition.groupOp}   cityId  ${condition.cityId.op}  #{condition.cityId.data}
            </if>
            <if test="condition.cityName!=null">
                ${condition.groupOp}   cityName  ${condition.cityName.op}  #{condition.cityName.data}
            </if>
            <if test="condition.countyId!=null">
                ${condition.groupOp}   countyId  ${condition.countyId.op}  #{condition.countyId.data}
            </if>
            <if test="condition.countyName!=null">
                ${condition.groupOp}   countyName  ${condition.countyName.op}  #{condition.countyName.data}
            </if>
            <if test="condition.batchType!=null">
                ${condition.groupOp}   batchType  ${condition.batchType.op}  #{condition.batchType.data}
            </if>


    </where>

        <if test="orderBy!=null">
        ORDER BY ${orderBy} ${sortBy}
        </if>
        <if test="offset != null">
            limit ${offset}, ${rows}
        </if>
    </select>

    <select id="like" parameterType="java.util.Map" resultType="University">
        SELECT
        <include refid="Base_Column_List" />
        FROM gk_university
        <trim prefix="WHERE" prefixOverrides="AND | OR">
            <if test="id!=null">
                AND id like CONCAT('%', #{id} , '%')
            </if>
            <if test="createDate!=null">
                AND createDate like CONCAT('%', #{createDate} , '%')
            </if>
            <if test="status!=null">
                AND status like CONCAT('%', #{status} , '%')
            </if>
            <if test="creator!=null">
                AND creator like CONCAT('%', #{creator} , '%')
            </if>
            <if test="lastModDate!=null">
                AND lastModDate like CONCAT('%', #{lastModDate} , '%')
            </if>
            <if test="lastModifier!=null">
                AND lastModifier like CONCAT('%', #{lastModifier} , '%')
            </if>
            <if test="code!=null">
                AND code like CONCAT('%', #{code} , '%')
            </if>
            <if test="name!=null">
                AND name like CONCAT('%', #{name} , '%')
            </if>
            <if test="subjection!=null">
                AND subjection like CONCAT('%', #{subjection} , '%')
            </if>
            <if test="educationLevel!=null">
                AND educationLevel like CONCAT('%', #{educationLevel} , '%')
            </if>
            <if test="property!=null">
                AND property like CONCAT('%', #{property} , '%')
            </if>
            <if test="type!=null">
                AND type like CONCAT('%', #{type} , '%')
            </if>
            <if test="url!=null">
                AND url like CONCAT('%', #{url} , '%')
            </if>
            <if test="address!=null">
                AND address like CONCAT('%', #{address} , '%')
            </if>
            <if test="contactPhone!=null">
                AND contactPhone like CONCAT('%', #{contactPhone} , '%')
            </if>
            <if test="entranceIntro!=null">
                AND entranceIntro like CONCAT('%', #{entranceIntro} , '%')
            </if>
            <if test="universityIntro!=null">
                AND universityIntro like CONCAT('%', #{universityIntro} , '%')
            </if>
            <if test="provinceId!=null">
                AND provinceId like CONCAT('%', #{provinceId} , '%')
            </if>
            <if test="provinceName!=null">
                AND provinceName like CONCAT('%', #{provinceName} , '%')
            </if>
            <if test="cityId!=null">
                AND cityId like CONCAT('%', #{cityId} , '%')
            </if>
            <if test="cityName!=null">
                AND cityName like CONCAT('%', #{cityName} , '%')
            </if>
            <if test="countyId!=null">
                AND countyId like CONCAT('%', #{countyId} , '%')
            </if>
            <if test="countyName!=null">
                AND countyName like CONCAT('%', #{countyName} , '%')
            </if>
            <if test="batchType!=null">
                AND batchType like CONCAT('%', #{batchType} , '%')
            </if>
        </trim>
        <if test="orderBy!=null">
        ORDER BY ${orderBy} ${sortBy}
        </if>
    </select>


    <select id="queryList" parameterType="java.util.Map" resultType="University">
        SELECT
        <include refid="Base_Column_List" />
        FROM gk_university
        <trim prefix="WHERE" prefixOverrides="AND | OR">
            <if test="condition.id!=null">
                AND id = #{condition.id}
            </if>
            <if test="condition.createDate!=null">
                AND createDate = #{condition.createDate}
            </if>
            <if test="condition.status!=null">
                AND status = #{condition.status}
            </if>
            <if test="condition.creator!=null">
                AND creator = #{condition.creator}
            </if>
            <if test="condition.lastModDate!=null">
                AND lastModDate = #{condition.lastModDate}
            </if>
            <if test="condition.lastModifier!=null">
                AND lastModifier = #{condition.lastModifier}
            </if>
            <if test="condition.code!=null">
                AND code = #{condition.code}
            </if>
            <if test="condition.name!=null">
                AND name = #{condition.name}
            </if>
            <if test="condition.subjection!=null">
                AND subjection = #{condition.subjection}
            </if>
            <if test="condition.educationLevel!=null">
                AND educationLevel = #{condition.educationLevel}
            </if>
            <if test="condition.property!=null">
                AND property = #{condition.property}
            </if>
            <if test="condition.type!=null">
                AND type = #{condition.type}
            </if>
            <if test="condition.url!=null">
                AND url = #{condition.url}
            </if>
            <if test="condition.address!=null">
                AND address = #{condition.address}
            </if>
            <if test="condition.contactPhone!=null">
                AND contactPhone = #{condition.contactPhone}
            </if>
            <if test="condition.entranceIntro!=null">
                AND entranceIntro = #{condition.entranceIntro}
            </if>
            <if test="condition.universityIntro!=null">
                AND universityIntro = #{condition.universityIntro}
            </if>
            <if test="condition.provinceId!=null">
                AND provinceId = #{condition.provinceId}
            </if>
            <if test="condition.provinceName!=null">
                AND provinceName = #{condition.provinceName}
            </if>
            <if test="condition.cityId!=null">
                AND cityId = #{condition.cityId}
            </if>
            <if test="condition.cityName!=null">
                AND cityName = #{condition.cityName}
            </if>
            <if test="condition.countyId!=null">
                AND countyId = #{condition.countyId}
            </if>
            <if test="condition.countyName!=null">
                AND countyName = #{condition.countyName}
            </if>
            <if test="condition.batchType!=null">
                AND batchType = #{condition.batchType}
            </if>
        </trim>
        <if test="orderBy!=null">
        ORDER BY ${orderBy} ${sortBy}
        </if>
    </select>

    <select id="queryOne" parameterType="java.util.Map" resultType="University">
        SELECT
        <include refid="Base_Column_List" />
        FROM gk_university
        <trim prefix="WHERE" prefixOverrides="AND | OR">
            <if test="id!=null">
                AND id = #{id}
            </if>
            <if test="createDate!=null">
                AND createDate = #{createDate}
            </if>
            <if test="status!=null">
                AND status = #{status}
            </if>
            <if test="creator!=null">
                AND creator = #{creator}
            </if>
            <if test="lastModDate!=null">
                AND lastModDate = #{lastModDate}
            </if>
            <if test="lastModifier!=null">
                AND lastModifier = #{lastModifier}
            </if>
            <if test="code!=null">
                AND code = #{code}
            </if>
            <if test="name!=null">
                AND name = #{name}
            </if>
            <if test="subjection!=null">
                AND subjection = #{subjection}
            </if>
            <if test="educationLevel!=null">
                AND educationLevel = #{educationLevel}
            </if>
            <if test="property!=null">
                AND property = #{property}
            </if>
            <if test="type!=null">
                AND type = #{type}
            </if>
            <if test="url!=null">
                AND url = #{url}
            </if>
            <if test="address!=null">
                AND address = #{address}
            </if>
            <if test="contactPhone!=null">
                AND contactPhone = #{contactPhone}
            </if>
            <if test="entranceIntro!=null">
                AND entranceIntro = #{entranceIntro}
            </if>
            <if test="universityIntro!=null">
                AND universityIntro = #{universityIntro}
            </if>
            <if test="provinceId!=null">
                AND provinceId = #{provinceId}
            </if>
            <if test="provinceName!=null">
                AND provinceName = #{provinceName}
            </if>
            <if test="cityId!=null">
                AND cityId = #{cityId}
            </if>
            <if test="cityName!=null">
                AND cityName = #{cityName}
            </if>
            <if test="countyId!=null">
                AND countyId = #{countyId}
            </if>
            <if test="countyName!=null">
                AND countyName = #{countyName}
            </if>
            <if test="batchType!=null">
                AND batchType = #{batchType}
            </if>
        </trim>
        limit 0,1
    </select>

    <select id="count" resultType="java.lang.Integer">
        SELECT count(id) FROM gk_university
       <where>
           <if test="id!=null">
               ${groupOp} id ${id.op}  #{id.data}
           </if>
           <if test="createDate!=null">
               ${groupOp} createDate ${createDate.op}  #{createDate.data}
           </if>
           <if test="status!=null">
               ${groupOp} status ${status.op}  #{status.data}
           </if>
           <if test="creator!=null">
               ${groupOp} creator ${creator.op}  #{creator.data}
           </if>
           <if test="lastModDate!=null">
               ${groupOp} lastModDate ${lastModDate.op}  #{lastModDate.data}
           </if>
           <if test="lastModifier!=null">
               ${groupOp} lastModifier ${lastModifier.op}  #{lastModifier.data}
           </if>
           <if test="code!=null">
               ${groupOp} code ${code.op}  #{code.data}
           </if>
           <if test="name!=null">
               ${groupOp} name ${name.op}  #{name.data}
           </if>
           <if test="subjection!=null">
               ${groupOp} subjection ${subjection.op}  #{subjection.data}
           </if>
           <if test="educationLevel!=null">
               ${groupOp} educationLevel ${educationLevel.op}  #{educationLevel.data}
           </if>
           <if test="property!=null">
               ${groupOp} property ${property.op}  #{property.data}
           </if>
           <if test="type!=null">
               ${groupOp} type ${type.op}  #{type.data}
           </if>
           <if test="url!=null">
               ${groupOp} url ${url.op}  #{url.data}
           </if>
           <if test="address!=null">
               ${groupOp} address ${address.op}  #{address.data}
           </if>
           <if test="contactPhone!=null">
               ${groupOp} contactPhone ${contactPhone.op}  #{contactPhone.data}
           </if>
           <if test="entranceIntro!=null">
               ${groupOp} entranceIntro ${entranceIntro.op}  #{entranceIntro.data}
           </if>
           <if test="universityIntro!=null">
               ${groupOp} universityIntro ${universityIntro.op}  #{universityIntro.data}
           </if>
           <if test="provinceId!=null">
               ${groupOp} provinceId ${provinceId.op}  #{provinceId.data}
           </if>
           <if test="provinceName!=null">
               ${groupOp} provinceName ${provinceName.op}  #{provinceName.data}
           </if>
           <if test="cityId!=null">
               ${groupOp} cityId ${cityId.op}  #{cityId.data}
           </if>
           <if test="cityName!=null">
               ${groupOp} cityName ${cityName.op}  #{cityName.data}
           </if>
           <if test="countyId!=null">
               ${groupOp} countyId ${countyId.op}  #{countyId.data}
           </if>
           <if test="countyName!=null">
               ${groupOp} countyName ${countyName.op}  #{countyName.data}
           </if>
           <if test="batchType!=null">
               ${groupOp} batchType ${batchType.op}  #{batchType.data}
           </if>

       </where>
    <if test="orderBy!=null">
        ORDER BY ${orderBy} ${sortBy}
    </if>
    </select>

    <select id="selectMaxId" resultType="java.lang.Long">
        SELECT
        MAX(id)
        FROM gk_university
    </select>



    <select id="getUniversityList" parameterType="java.util.Map" resultType="UniversityDto">
          select a.code,a.name,a.subjection,a.educationLevel as educatLevel,a.type as universityType, b.name as property,a.address,a.contactPhone,a.provinceName,a.url from gk_university a
        left join gk_university_dict  b on b.type='FEATURE' and b.dictId=a.property

        where 1=1
            <if test="universityQuery.province!=null and universityQuery.province!='' ">
                and a.provinceName = #{universityQuery.province}
            </if>

            <if test="universityQuery.universtiyType!=null and universityQuery.universtiyType!=''">
                and a.type=#{universityQuery.universtiyType}
            </if>

            <if test="universityQuery.batch!=null and universityQuery.batch!=''">
                and a.batchType in
                <foreach collection="universityQuery.batch" item="item" index="index" open="(" separator="," close=")">
                    #{item}
                </foreach>
             </if>

            <if test="universityQuery.feature!=null and universityQuery.feature!=''">
                and a.property in

                <foreach collection="universityQuery.feature" item="item" index="index" open="(" separator="," close=")">
                    #{item}
                </foreach>
            </if>
           <if test="universityQuery.searchName!=null and universityQuery.searchName!=''">
                and a.name like concat('%',#{universityQuery.searchName},'%')
           </if>
          limit #{universityQuery.start},#{universityQuery.end}
      </select>


    <select id="getUniversityCount" parameterType="java.util.Map" resultType="java.lang.Integer">
        select count(*) from gk_university where 1=1
        <if test="universityQuery.province!=null and universityQuery.province!='' ">
            and provinceName = #{universityQuery.province}
        </if>

        <if test="universityQuery.universtiyType!=null and universityQuery.universtiyType!=''">
            and type=#{universityQuery.universtiyType}
        </if>

        <if test="universityQuery.batch!=null and universityQuery.batch!=''">
            and batchType in
            <foreach collection="universityQuery.batch" item="item" index="index" open="(" separator="," close=")">
                #{item}
            </foreach>
        </if>

        <if test="universityQuery.feature!=null and universityQuery.feature!=''">
            and property in

            <foreach collection="universityQuery.feature" item="item" index="index" open="(" separator="," close=")">
                #{item}
            </foreach>
        </if>
        <if test="universityQuery.searchName!=null and universityQuery.searchName!=''">
            and name like concat('%',#{universityQuery.searchName},'%')
        </if>
    </select>



    <select id="getUniversityDetail" parameterType="java.lang.String" resultType="UniversityDto">
        select a.code,a.name,a.subjection,c.name as educatLevel,a.type as universityType,b.name as property,a.address,a.contactPhone,
       '' as universityImage,a.provinceName,a.url from gk_university a left join gk_university_dict  b on b.type='FEATURE' and b.dictId=a.property

         left join gk_university_dict c on c.dictId=a.educationLevel and c.type='EDULEVEL'
        where 1=1 and code=#{code}
         <if test="batch!=null and batch != ''">
              and a.batchType=#{batch}
         </if>
          limit 0,1
    </select>


    <select id="getEnrollInfoByYear" parameterType="java.lang.String" resultType="EnrollInfo">
        select '文科' as subjectName, wsPlanNumber as planNumber,wsEnrollNumber as enrollNumber,wsHighestScore as highestScore,
        wsHighestRank as highestRank,wsLowestScore as lowestScore,wsLowestRank as lowestRank,wsAverageScore as averageScore,
          wsAverageRank as averageRank
         from gk_enroll_report where universityCode=#{code} and year=#{year}

        union all
        select '理工' as subjectName, lgPlanNumber as planNumber,lgEnrollNumber as enrollNumber,lgHighestScore as highestScore,
        lgHighestRank as highestRank,lgLowestScore as lowestScore,lgLowestRank as lowestRank,lgAverageScore as averageScore,
          lgAverageRank as averageRank
         from gk_enroll_report where universityCode=#{code} and year=#{year}

    </select>


    <select id="getPlanInfosByYear" parameterType="java.lang.String" resultType="PlanInfo">
        select majoredName,batch,subject,enrollNumber as planNumber,schoolLength,feeStandard  from gk_enroll_plan where 1=1
         and universityCode=#{code} and year=#{year}
          <if test="batch !=null and batch !=''">
               and batch=#{batch}
          </if>
    </select>



    <select id="getUniversityEnrollIntro" parameterType="java.lang.String" resultType="java.lang.String">
        select  entranceIntro from gk_university where 1=1
        and code=#{code} limit 0,1
    </select>


    <select id="getUniversityIntro" parameterType="java.lang.String" resultType="java.lang.String">
        select universityIntro from gk_university where 1=1
        and code=#{code} limit 0,1
    </select>
</mapper>

